{
  "project_info": {
    "project_number": "187456587043",
    "project_id": "e-citizen-portal-d5230",
    "storage_bucket": "e-citizen-portal-d5230.appspot.com"
  },
  "client": [
    {
      "client_info": {
        "mobilesdk_app_id": "1:187456587043:android:ff45991ccac970fab73896",
        "android_client_info": {
          "package_name": "com.e_citizen_portal"
        }
      },
      "oauth_client": [],
      "api_key": [
        {
          "current_key": "AIzaSyDvqCPxUcAPeUAT3tyaEC1QSwCOYcaxkRw"
        }
      ],
      "services": {
        "appinvite_service": {
          "other_platform_oauth_client": []
        }
      }
    }
  ],
  "configuration_version": "1"
}